docker_minecraft/__init__.py
docker_minecraft/__main__.py
docker_minecraft/lib.py
docker_minecraft-0.2.0.dist-info/entry_points.txt
docker_minecraft-0.2.0.dist-info/LICENSE.md
docker_minecraft-0.2.0.dist-info/METADATA
docker_minecraft-0.2.0.dist-info/WHEEL
docker_minecraft-0.2.0.dist-info/RECORD
