Metadata-Version: 2.1
Name: docker-minecraft
Version: 0.2.0
Summary: Make a Minecraft server in Docker, with one command.
Home-page: https://codeberg.org/osfanbuff63/docker-minecraft-cli
License: GPL-3.0-or-later
Author: osfanbuff63
Author-email: osfanbuff63@osfanbuff63.tech
Requires-Python: >=3.11,<4
Classifier: License :: OSI Approved :: GNU General Public License v3 or later (GPLv3+)
Classifier: Programming Language :: Python :: 3
Classifier: Programming Language :: Python :: 3.11
Requires-Dist: click (>=8.1.3,<9.0.0)
Requires-Dist: docker (>=6.0.1,<7.0.0)
Requires-Dist: requests (>=2.28.2,<3.0.0)
Requires-Dist: tomlkit (>=0.11.6,<0.12.0)
Project-URL: Documentation, https://docker-minecraft.osfanbuff63.tech
Project-URL: Repository, https://codeberg.org/osfanbuff63/docker-minecraft-cli
